gif_pygame/__init__.py
gif_pygame/_common.py
gif_pygame/gif_pygame.py
gif_pygame/transform.py
gif_pygame-1.2.0.dist-info/licenses/LICENSE
gif_pygame-1.2.0.dist-info/METADATA
gif_pygame-1.2.0.dist-info/WHEEL
gif_pygame-1.2.0.dist-info/top_level.txt
gif_pygame-1.2.0.dist-info/RECORD
